setup.py
geo_utils.egg-info/PKG-INFO
geo_utils.egg-info/SOURCES.txt
geo_utils.egg-info/dependency_links.txt
geo_utils.egg-info/requires.txt
geo_utils.egg-info/top_level.txt
tests/__init__.py
tests/vtown/__init__.py
tests/vtown/geo/__init__.py
tests/vtown/geo/polygon_tests.py
vtown/__init__.py
vtown/geo/__init__.py
vtown/geo/polygon.py
vtown/geo/private.py