Metadata-Version: 1.0
Name: geo-utils
Version: 0.1
Summary: Miscellaneous geospatial utilities.
Home-page: http://github.com/isterin/geo-utils
Author: Ilya Sterin
Author-email: UNKNOWN
License: BSD
Platform: UNKNOWN
Classifier: Development Status :: 3 - Alpha
Classifier: License :: OSI Approved :: BSD License
Classifier: Operating System :: OS Independent
Classifier: Programming Language :: Python :: 2.6
